[{"tick":9,"events":[{"id":"summon_lightning_strike","instanceId":"evt-4d89bbca"}]},{"tick":18,"events":[{"id":"meteor_strike","instanceId":"evt-bce6a2c1"}]},{"tick":32,"events":[{"id":"magnet_pull","instanceId":"evt-399dce3e"}]},{"tick":42,"events":[{"id":"rocket_boost","instanceId":"evt-739ed4d4"}]},{"tick":49,"events":[{"id":"temporary_shield","instanceId":"evt-5238301c"}]},{"tick":56,"events":[{"id":"hook_shot","instanceId":"evt-2b7b2179"}]},{"tick":75,"events":[{"id":"temporary_shield","instanceId":"evt-cdad68fd"}]},{"tick":83,"events":[{"id":"ice_patch","instanceId":"evt-61b8f186"}]},{"tick":93,"events":[{"id":"lightning_strike","instanceId":"evt-7710c6ba"}]},{"tick":94,"events":[{"id":"bomb_throw","instanceId":"evt-42e46ae9"},{"id":"summon_lightning_strike","instanceId":"evt-9daa9ec8"}]},{"tick":127,"events":[{"id":"position_swap","instanceId":"evt-23aa20e5"}]},{"tick":133,"events":[{"id":"hook_shot","instanceId":"evt-024eb078"}]},{"tick":139,"events":[{"id":"aerial_duel","instanceId":"evt-e3d76a3c"}]},{"tick":141,"events":[{"id":"tidal_wave","instanceId":"evt-a40342b3"}]},{"tick":172,"events":[{"id":"tidal_wave","instanceId":"evt-5d85a929"}]},{"tick":188,"events":[{"id":"temporary_shield","instanceId":"evt-d2f2a4c8"}]},{"tick":194,"events":[{"id":"smg_attack","instanceId":"evt-22d3475e"}]},{"tick":199,"events":[{"id":"earthquake","instanceId":"evt-0296b0e3"}]},{"tick":210,"events":[{"id":"lightning_strike","instanceId":"evt-8cf4ee6f"}]},{"tick":211,"events":[{"id":"smg_attack","instanceId":"evt-0dd5ad7d"}]},{"tick":234,"events":[{"id":"summon_lightning_strike","instanceId":"evt-a9294ffa"}]},{"tick":235,"events":[{"id":"samurai_duel","instanceId":"evt-f973c45f"}]},{"tick":240,"events":[{"id":"position_swap","instanceId":"evt-99e88058"}]},{"tick":252,"events":[{"id":"lightning_strike","instanceId":"evt-2770cd9c"}]},{"tick":254,"events":[{"id":"rocket_boost","instanceId":"evt-3173153e"}]},{"tick":257,"events":[{"id":"luck_charm","instanceId":"evt-bc4bf3d7"}]},{"tick":265,"events":[{"id":"tornado","instanceId":"evt-f48bb742"}]},{"tick":271,"events":[{"id":"samurai_duel","instanceId":"evt-71d3c98c"},{"id":"earthquake","instanceId":"evt-42cef39c"}]},{"tick":273,"events":[{"id":"hook_shot","instanceId":"evt-2c5b9e28"}]},{"tick":275,"events":[{"id":"rocket_boost","instanceId":"evt-87460c7b"}]},{"tick":289,"events":[{"id":"hook_shot","instanceId":"evt-897e989d"}]},{"tick":295,"events":[{"id":"ice_patch","instanceId":"evt-6d85856e"}]},{"tick":297,"events":[{"id":"smg_attack","instanceId":"evt-5f0e6ddf"}]},{"tick":300,"events":[{"id":"tornado","instanceId":"evt-e42efeeb"}]},{"tick":317,"events":[{"id":"temporary_shield","instanceId":"evt-04be3975"}]},{"tick":352,"events":[{"id":"hook_shot","instanceId":"evt-7bb02e47"}]},{"tick":360,"events":[{"id":"ice_patch","instanceId":"evt-0adfcb01"}]},{"tick":368,"events":[{"id":"meteor_strike","instanceId":"evt-e70540cb"}]},{"tick":372,"events":[{"id":"bomb_throw","instanceId":"evt-b9246c21"}]},{"tick":379,"events":[{"id":"magnet_pull","instanceId":"evt-b833d97d"}]},{"tick":388,"events":[{"id":"luck_charm","instanceId":"evt-17810bc4"}]},{"tick":399,"events":[{"id":"aerial_duel","instanceId":"evt-d088b5a4"}]},{"tick":400,"events":[{"id":"bomb_throw","instanceId":"evt-b749faba"}]}]