[{"tick":19,"events":[{"id":"summon_lightning_strike","instanceId":"evt-8be5dba0"}]},{"tick":20,"events":[{"id":"smg_attack","instanceId":"evt-865b0b97"}]},{"tick":23,"events":[{"id":"temporary_shield","instanceId":"evt-34bc6683"}]},{"tick":28,"events":[{"id":"aerial_duel","instanceId":"evt-317e2a0d"}]},{"tick":42,"events":[{"id":"temporary_shield","instanceId":"evt-c8c31b65"}]},{"tick":96,"events":[{"id":"hook_shot","instanceId":"evt-e7b0c47d"}]},{"tick":111,"events":[{"id":"meteor_strike","instanceId":"evt-c4adc8f1"}]},{"tick":120,"events":[{"id":"temporary_shield","instanceId":"evt-44991536"}]},{"tick":121,"events":[{"id":"magnet_pull","instanceId":"evt-ed1904c8"}]},{"tick":125,"events":[{"id":"hook_shot","instanceId":"evt-9f2f2ee1"}]},{"tick":132,"events":[{"id":"tidal_wave","instanceId":"evt-705de65e"}]},{"tick":141,"events":[{"id":"aerial_duel","instanceId":"evt-5f711df8"}]},{"tick":143,"events":[{"id":"rocket_boost","instanceId":"evt-0e9b74c6"}]},{"tick":147,"events":[{"id":"temporary_shield","instanceId":"evt-80586c15"}]},{"tick":166,"events":[{"id":"ice_patch","instanceId":"evt-4ffad75d"}]},{"tick":168,"events":[{"id":"lightning_strike","instanceId":"evt-0c6b44ca"}]},{"tick":171,"events":[{"id":"rocket_boost","instanceId":"evt-d7e85d7f"}]},{"tick":185,"events":[{"id":"position_swap","instanceId":"evt-919c63b9"}]},{"tick":187,"events":[{"id":"samurai_duel","instanceId":"evt-ed85b2ac"}]},{"tick":197,"events":[{"id":"hook_shot","instanceId":"evt-1ac2fa57"}]},{"tick":207,"events":[{"id":"smg_attack","instanceId":"evt-e21610c5"}]},{"tick":219,"events":[{"id":"earthquake","instanceId":"evt-1a367a36"}]},{"tick":220,"events":[{"id":"chain_reaction","instanceId":"evt-9c7a62b5"}]},{"tick":224,"events":[{"id":"smg_attack","instanceId":"evt-19a1dd47"}]},{"tick":226,"events":[{"id":"bomb_throw","instanceId":"evt-3f11d063"}]},{"tick":229,"events":[{"id":"lightning_strike","instanceId":"evt-9f260c3d"}]},{"tick":238,"events":[{"id":"position_swap","instanceId":"evt-7a7e6e26"}]},{"tick":240,"events":[{"id":"rocket_boost","instanceId":"evt-06079b03"}]},{"tick":243,"events":[{"id":"earthquake","instanceId":"evt-7b5e835d"}]},{"tick":256,"events":[{"id":"luck_charm","instanceId":"evt-62bde331"}]},{"tick":268,"events":[{"id":"bomb_throw","instanceId":"evt-539e4b00"}]},{"tick":275,"events":[{"id":"meteor_strike","instanceId":"evt-62685486"}]},{"tick":282,"events":[{"id":"tidal_wave","instanceId":"evt-dca740e6"}]},{"tick":284,"events":[{"id":"ice_patch","instanceId":"evt-e5862b0f"}]},{"tick":289,"events":[{"id":"tornado","instanceId":"evt-08da991f"}]},{"tick":298,"events":[{"id":"summon_lightning_strike","instanceId":"evt-d6c3f04e"}]},{"tick":307,"events":[{"id":"ice_patch","instanceId":"evt-6aff60ca"}]},{"tick":315,"events":[{"id":"chain_reaction","instanceId":"evt-97649864"}]},{"tick":331,"events":[{"id":"summon_lightning_strike","instanceId":"evt-cfe94983"}]},{"tick":337,"events":[{"id":"samurai_duel","instanceId":"evt-99cf23e8"}]},{"tick":365,"events":[{"id":"magnet_pull","instanceId":"evt-b65e5612"}]},{"tick":372,"events":[{"id":"tornado","instanceId":"evt-b17ebf01"}]},{"tick":396,"events":[{"id":"hook_shot","instanceId":"evt-bd9b7438"}]}]