[{"tick":1,"events":[{"id":"temporary_shield","instanceId":"evt-f9133e01"}]},{"tick":4,"events":[{"id":"aerial_duel","instanceId":"evt-68f7f64f"}]},{"tick":14,"events":[{"id":"position_swap","instanceId":"evt-3fd2cdb0"}]},{"tick":26,"events":[{"id":"summon_lightning_strike","instanceId":"evt-a9d78603"}]},{"tick":33,"events":[{"id":"smg_attack","instanceId":"evt-b2ca3c8f"}]},{"tick":40,"events":[{"id":"hook_shot","instanceId":"evt-f3481170"}]},{"tick":46,"events":[{"id":"samurai_duel","instanceId":"evt-b72f0e74"}]},{"tick":61,"events":[{"id":"aerial_duel","instanceId":"evt-f2796c1b"}]},{"tick":74,"events":[{"id":"bomb_throw","instanceId":"evt-7dd9ea40"}]},{"tick":79,"events":[{"id":"hook_shot","instanceId":"evt-5379bf62"}]},{"tick":88,"events":[{"id":"rocket_boost","instanceId":"evt-1092abd0"}]},{"tick":90,"events":[{"id":"earthquake","instanceId":"evt-12f2ef07"}]},{"tick":95,"events":[{"id":"tornado","instanceId":"evt-b7614f77"}]},{"tick":97,"events":[{"id":"ice_patch","instanceId":"evt-1428dac8"}]},{"tick":112,"events":[{"id":"meteor_strike","instanceId":"evt-73e45d83"}]},{"tick":115,"events":[{"id":"samurai_duel","instanceId":"evt-a97e3977"}]},{"tick":121,"events":[{"id":"chain_reaction","instanceId":"evt-73d3d936"}]},{"tick":122,"events":[{"id":"magnet_pull","instanceId":"evt-5a41dd3d"},{"id":"lightning_strike","instanceId":"evt-033fb30a"}]},{"tick":123,"events":[{"id":"hook_shot","instanceId":"evt-abba976f"}]},{"tick":129,"events":[{"id":"bomb_throw","instanceId":"evt-76f43544"}]},{"tick":131,"events":[{"id":"tidal_wave","instanceId":"evt-d7706eaa"}]},{"tick":162,"events":[{"id":"rocket_boost","instanceId":"evt-25222f9b"}]},{"tick":164,"events":[{"id":"position_swap","instanceId":"evt-bc83bc51"}]},{"tick":166,"events":[{"id":"bomb_throw","instanceId":"evt-d5f557e4"}]},{"tick":173,"events":[{"id":"ufo_abduction","instanceId":"evt-51053c56"}]},{"tick":182,"events":[{"id":"rocket_boost","instanceId":"evt-039515f6"},{"id":"temporary_shield","instanceId":"evt-3f066e5e"}]},{"tick":190,"events":[{"id":"tornado","instanceId":"evt-ae672df3"}]},{"tick":192,"events":[{"id":"smg_attack","instanceId":"evt-92981228"}]},{"tick":207,"events":[{"id":"temporary_shield","instanceId":"evt-d14c3cce"}]},{"tick":221,"events":[{"id":"summon_lightning_strike","instanceId":"evt-7291f86d"}]},{"tick":226,"events":[{"id":"temporary_shield","instanceId":"evt-8ca68e73"}]},{"tick":249,"events":[{"id":"lightning_strike","instanceId":"evt-ac7ce723"}]},{"tick":272,"events":[{"id":"ice_patch","instanceId":"evt-1cedd073"}]},{"tick":293,"events":[{"id":"lightning_strike","instanceId":"evt-d24cd335"}]},{"tick":307,"events":[{"id":"temporary_shield","instanceId":"evt-192d01ff"},{"id":"magnet_pull","instanceId":"evt-d6064ab3"}]},{"tick":308,"events":[{"id":"ice_patch","instanceId":"evt-ce217cac"}]},{"tick":327,"events":[{"id":"chain_reaction","instanceId":"evt-400b41ed"}]},{"tick":331,"events":[{"id":"earthquake","instanceId":"evt-cb188c0e"}]},{"tick":333,"events":[{"id":"tidal_wave","instanceId":"evt-92a869b6"}]},{"tick":339,"events":[{"id":"meteor_strike","instanceId":"evt-74fa1e02"}]},{"tick":347,"events":[{"id":"hook_shot","instanceId":"evt-48140e51"}]},{"tick":370,"events":[{"id":"smg_attack","instanceId":"evt-a39fb437"}]},{"tick":397,"events":[{"id":"magnet_pull","instanceId":"evt-95a7dd4c"}]}]