[{"tick":27,"events":[{"id":"temporary_shield","instanceId":"evt-3860f81b"}]},{"tick":28,"events":[{"id":"smg_attack","instanceId":"evt-66635eb2"}]},{"tick":31,"events":[{"id":"hook_shot","instanceId":"evt-68a02b9f"}]},{"tick":42,"events":[{"id":"rocket_boost","instanceId":"evt-52157685"},{"id":"summon_lightning_strike","instanceId":"evt-a7f299bb"}]},{"tick":63,"events":[{"id":"hook_shot","instanceId":"evt-2d74c179"}]},{"tick":65,"events":[{"id":"position_swap","instanceId":"evt-17a0f333"}]},{"tick":66,"events":[{"id":"ice_patch","instanceId":"evt-c98677a7"}]},{"tick":68,"events":[{"id":"bomb_throw","instanceId":"evt-8541cff9"}]},{"tick":80,"events":[{"id":"tidal_wave","instanceId":"evt-b8a01aac"}]},{"tick":87,"events":[{"id":"samurai_duel","instanceId":"evt-9d5ba1ce"}]},{"tick":117,"events":[{"id":"temporary_shield","instanceId":"evt-2352f7e4"}]},{"tick":123,"events":[{"id":"summon_lightning_strike","instanceId":"evt-03670ce1"}]},{"tick":126,"events":[{"id":"lightning_strike","instanceId":"evt-80453396"}]},{"tick":152,"events":[{"id":"magnet_pull","instanceId":"evt-feb2669d"}]},{"tick":156,"events":[{"id":"tornado","instanceId":"evt-135c4d75"}]},{"tick":162,"events":[{"id":"hook_shot","instanceId":"evt-7f447bda"}]},{"tick":172,"events":[{"id":"chain_reaction","instanceId":"evt-3a6c70a6"}]},{"tick":173,"events":[{"id":"tornado","instanceId":"evt-c359d806"}]},{"tick":175,"events":[{"id":"luck_charm","instanceId":"evt-24e37cb5"}]},{"tick":222,"events":[{"id":"rocket_boost","instanceId":"evt-c3cd4e1c"}]},{"tick":224,"events":[{"id":"bomb_throw","instanceId":"evt-f036234c"}]},{"tick":234,"events":[{"id":"hook_shot","instanceId":"evt-8bd8a9fe"}]},{"tick":245,"events":[{"id":"earthquake","instanceId":"evt-46ed1988"}]},{"tick":246,"events":[{"id":"tidal_wave","instanceId":"evt-345721ad"}]},{"tick":250,"events":[{"id":"ice_patch","instanceId":"evt-d5896b1d"}]},{"tick":252,"events":[{"id":"summon_lightning_strike","instanceId":"evt-af190db8"}]},{"tick":264,"events":[{"id":"hook_shot","instanceId":"evt-f5e01bd8"}]},{"tick":271,"events":[{"id":"temporary_shield","instanceId":"evt-bada2354"}]},{"tick":274,"events":[{"id":"meteor_strike","instanceId":"evt-db02b8c4"}]},{"tick":287,"events":[{"id":"smg_attack","instanceId":"evt-5386954d"}]},{"tick":293,"events":[{"id":"samurai_duel","instanceId":"evt-8f65a881"}]},{"tick":300,"events":[{"id":"bomb_throw","instanceId":"evt-c9bf0c94"}]},{"tick":310,"events":[{"id":"rocket_boost","instanceId":"evt-784ef0d8"}]},{"tick":326,"events":[{"id":"aerial_duel","instanceId":"evt-1e2e69f1"}]},{"tick":332,"events":[{"id":"smg_attack","instanceId":"evt-fc749209"},{"id":"lightning_strike","instanceId":"evt-87a8fa14"}]},{"tick":351,"events":[{"id":"position_swap","instanceId":"evt-875af12e"}]},{"tick":363,"events":[{"id":"aerial_duel","instanceId":"evt-ccb39b29"},{"id":"lightning_strike","instanceId":"evt-756b651f"}]},{"tick":366,"events":[{"id":"meteor_strike","instanceId":"evt-309858d9"}]},{"tick":373,"events":[{"id":"ice_patch","instanceId":"evt-bb87b2b7"}]},{"tick":386,"events":[{"id":"temporary_shield","instanceId":"evt-b8c9c657"}]},{"tick":387,"events":[{"id":"ufo_abduction","instanceId":"evt-34c96280"},{"id":"magnet_pull","instanceId":"evt-bc8cdb0d"}]}]