[{"tick":3,"events":[{"id":"temporary_shield","instanceId":"evt-4b2d8abb"}]},{"tick":7,"events":[{"id":"lightning_strike","instanceId":"evt-aadb24d0"}]},{"tick":16,"events":[{"id":"meteor_strike","instanceId":"evt-9476aef2"}]},{"tick":62,"events":[{"id":"temporary_shield","instanceId":"evt-f2239b16"}]},{"tick":70,"events":[{"id":"bomb_throw","instanceId":"evt-0f1fbf5b"}]},{"tick":80,"events":[{"id":"smg_attack","instanceId":"evt-4b758360"}]},{"tick":86,"events":[{"id":"hook_shot","instanceId":"evt-2f878160"}]},{"tick":92,"events":[{"id":"magnet_pull","instanceId":"evt-5dbef392"}]},{"tick":113,"events":[{"id":"lightning_strike","instanceId":"evt-9b0b7041"}]},{"tick":129,"events":[{"id":"temporary_shield","instanceId":"evt-db6fb606"}]},{"tick":138,"events":[{"id":"summon_lightning_strike","instanceId":"evt-ffd52e01"}]},{"tick":139,"events":[{"id":"tidal_wave","instanceId":"evt-2f1fbf9c"}]},{"tick":144,"events":[{"id":"earthquake","instanceId":"evt-1c9502f4"}]},{"tick":152,"events":[{"id":"hook_shot","instanceId":"evt-1b7c5704"}]},{"tick":160,"events":[{"id":"luck_charm","instanceId":"evt-be1fe084"}]},{"tick":172,"events":[{"id":"chain_reaction","instanceId":"evt-217b89d6"}]},{"tick":173,"events":[{"id":"tornado","instanceId":"evt-5b86be1d"}]},{"tick":181,"events":[{"id":"rocket_boost","instanceId":"evt-f6da13d0"}]},{"tick":191,"events":[{"id":"ice_patch","instanceId":"evt-3a991fdb"}]},{"tick":192,"events":[{"id":"summon_lightning_strike","instanceId":"evt-942b7278"}]},{"tick":196,"events":[{"id":"position_swap","instanceId":"evt-63dd8256"}]},{"tick":197,"events":[{"id":"samurai_duel","instanceId":"evt-31bf17f7"}]},{"tick":211,"events":[{"id":"aerial_duel","instanceId":"evt-def8f5d6"}]},{"tick":231,"events":[{"id":"magnet_pull","instanceId":"evt-e621313b"}]},{"tick":250,"events":[{"id":"temporary_shield","instanceId":"evt-7651048f"}]},{"tick":255,"events":[{"id":"smg_attack","instanceId":"evt-25addd94"}]},{"tick":256,"events":[{"id":"meteor_strike","instanceId":"evt-6f146745"}]},{"tick":259,"events":[{"id":"summon_lightning_strike","instanceId":"evt-0af10fc4"}]},{"tick":267,"events":[{"id":"tornado","instanceId":"evt-978f5f78"}]},{"tick":269,"events":[{"id":"ice_patch","instanceId":"evt-398ed24c"}]},{"tick":276,"events":[{"id":"temporary_shield","instanceId":"evt-7efe8922"}]},{"tick":292,"events":[{"id":"ice_patch","instanceId":"evt-349ba1bc"}]},{"tick":296,"events":[{"id":"aerial_duel","instanceId":"evt-f2f02885"}]},{"tick":302,"events":[{"id":"rocket_boost","instanceId":"evt-017af04a"}]},{"tick":313,"events":[{"id":"smg_attack","instanceId":"evt-40987bd1"}]},{"tick":318,"events":[{"id":"hook_shot","instanceId":"evt-589fc9b6"}]},{"tick":321,"events":[{"id":"luck_charm","instanceId":"evt-f5770208"}]},{"tick":326,"events":[{"id":"magnet_pull","instanceId":"evt-9032506a"}]},{"tick":341,"events":[{"id":"samurai_duel","instanceId":"evt-5a011e04"}]},{"tick":348,"events":[{"id":"earthquake","instanceId":"evt-8cf5a908"}]},{"tick":356,"events":[{"id":"tidal_wave","instanceId":"evt-f62620d0"}]},{"tick":361,"events":[{"id":"position_swap","instanceId":"evt-53144207"}]},{"tick":395,"events":[{"id":"bomb_throw","instanceId":"evt-2a2f50e2"},{"id":"chain_reaction","instanceId":"evt-f5f70e1d"}]},{"tick":399,"events":[{"id":"lightning_strike","instanceId":"evt-545a4706"}]}]