[{"tick":8,"events":[{"id":"aerial_duel","instanceId":"evt-6a3b50e3"}]},{"tick":15,"events":[{"id":"ice_patch","instanceId":"evt-cc8bac20"}]},{"tick":37,"events":[{"id":"magnet_pull","instanceId":"evt-eedb28a2"}]},{"tick":105,"events":[{"id":"magnet_pull","instanceId":"evt-1e10586e"}]},{"tick":116,"events":[{"id":"summon_lightning_strike","instanceId":"evt-e3a984e0"}]},{"tick":127,"events":[{"id":"smg_attack","instanceId":"evt-a3345cc1"}]},{"tick":133,"events":[{"id":"rocket_boost","instanceId":"evt-fb530a38"}]},{"tick":134,"events":[{"id":"bomb_throw","instanceId":"evt-55e2d70c"}]},{"tick":135,"events":[{"id":"luck_charm","instanceId":"evt-4cf7709f"}]},{"tick":145,"events":[{"id":"ice_patch","instanceId":"evt-c9d49756"}]},{"tick":146,"events":[{"id":"summon_lightning_strike","instanceId":"evt-bdb049c0"}]},{"tick":153,"events":[{"id":"tidal_wave","instanceId":"evt-0055ac9b"}]},{"tick":157,"events":[{"id":"ufo_abduction","instanceId":"evt-6c6e5656"}]},{"tick":167,"events":[{"id":"bomb_throw","instanceId":"evt-cc1d62d5"}]},{"tick":169,"events":[{"id":"smg_attack","instanceId":"evt-9c889d88"}]},{"tick":177,"events":[{"id":"rocket_boost","instanceId":"evt-7fdaf40f"}]},{"tick":185,"events":[{"id":"meteor_strike","instanceId":"evt-fd16ca3e"}]},{"tick":205,"events":[{"id":"temporary_shield","instanceId":"evt-68f2d095"}]},{"tick":211,"events":[{"id":"tornado","instanceId":"evt-6b59b89f"}]},{"tick":212,"events":[{"id":"lightning_strike","instanceId":"evt-42f83f94"}]},{"tick":224,"events":[{"id":"rocket_boost","instanceId":"evt-20410a87"}]},{"tick":225,"events":[{"id":"temporary_shield","instanceId":"evt-0a492de0"}]},{"tick":226,"events":[{"id":"luck_charm","instanceId":"evt-17e83d0b"}]},{"tick":228,"events":[{"id":"hook_shot","instanceId":"evt-537a22a8"}]},{"tick":239,"events":[{"id":"tidal_wave","instanceId":"evt-df57027a"}]},{"tick":240,"events":[{"id":"bomb_throw","instanceId":"evt-b1c15257"}]},{"tick":243,"events":[{"id":"tornado","instanceId":"evt-d707c643"}]},{"tick":254,"events":[{"id":"chain_reaction","instanceId":"evt-281ca5d7"}]},{"tick":256,"events":[{"id":"smg_attack","instanceId":"evt-45dd075a"}]},{"tick":272,"events":[{"id":"magnet_pull","instanceId":"evt-d8e39c0f"}]},{"tick":273,"events":[{"id":"lightning_strike","instanceId":"evt-5bfab78c"}]},{"tick":281,"events":[{"id":"temporary_shield","instanceId":"evt-a6920f9d"}]},{"tick":287,"events":[{"id":"samurai_duel","instanceId":"evt-7698894f"}]},{"tick":298,"events":[{"id":"temporary_shield","instanceId":"evt-02796de6"}]},{"tick":304,"events":[{"id":"earthquake","instanceId":"evt-38870c09"}]},{"tick":312,"events":[{"id":"hook_shot","instanceId":"evt-a7a50e9c"}]},{"tick":320,"events":[{"id":"meteor_strike","instanceId":"evt-08c920cd"}]},{"tick":331,"events":[{"id":"hook_shot","instanceId":"evt-10bd2dcc"}]},{"tick":333,"events":[{"id":"lightning_strike","instanceId":"evt-bd07100c"}]},{"tick":335,"events":[{"id":"position_swap","instanceId":"evt-b5380704"}]},{"tick":344,"events":[{"id":"temporary_shield","instanceId":"evt-1e78c252"}]},{"tick":355,"events":[{"id":"position_swap","instanceId":"evt-fbfce0f3"}]},{"tick":385,"events":[{"id":"summon_lightning_strike","instanceId":"evt-93bb3c0b"}]},{"tick":387,"events":[{"id":"ice_patch","instanceId":"evt-3a5cc331"}]},{"tick":394,"events":[{"id":"samurai_duel","instanceId":"evt-e311627c"}]},{"tick":395,"events":[{"id":"earthquake","instanceId":"evt-ea6972e7"}]}]