[{"tick":11,"events":[{"id":"lightning_strike","instanceId":"evt-c6767f1b"},{"id":"tornado","instanceId":"evt-5d14ee44"}]},{"tick":13,"events":[{"id":"ice_patch","instanceId":"evt-bccf77d6"}]},{"tick":27,"events":[{"id":"earthquake","instanceId":"evt-ea9dc99b"}]},{"tick":34,"events":[{"id":"meteor_strike","instanceId":"evt-5812877d"}]},{"tick":51,"events":[{"id":"position_swap","instanceId":"evt-8ca687c7"}]},{"tick":54,"events":[{"id":"tidal_wave","instanceId":"evt-49ab83b5"}]},{"tick":67,"events":[{"id":"magnet_pull","instanceId":"evt-02491bea"}]},{"tick":82,"events":[{"id":"bomb_throw","instanceId":"evt-0b2a5a22"}]},{"tick":108,"events":[{"id":"hook_shot","instanceId":"evt-8314f6fb"}]},{"tick":111,"events":[{"id":"magnet_pull","instanceId":"evt-87de0f66"}]},{"tick":121,"events":[{"id":"ufo_abduction","instanceId":"evt-4042983d"}]},{"tick":133,"events":[{"id":"luck_charm","instanceId":"evt-edb95e2c"}]},{"tick":141,"events":[{"id":"temporary_shield","instanceId":"evt-5b74aba3"}]},{"tick":142,"events":[{"id":"smg_attack","instanceId":"evt-643643a3"}]},{"tick":145,"events":[{"id":"samurai_duel","instanceId":"evt-72e28376"}]},{"tick":146,"events":[{"id":"rocket_boost","instanceId":"evt-83062d49"}]},{"tick":150,"events":[{"id":"bomb_throw","instanceId":"evt-021b98c6"},{"id":"magnet_pull","instanceId":"evt-7f280fb0"}]},{"tick":164,"events":[{"id":"position_swap","instanceId":"evt-c0131976"}]},{"tick":176,"events":[{"id":"hook_shot","instanceId":"evt-b2435f48"}]},{"tick":179,"events":[{"id":"lightning_strike","instanceId":"evt-789d421a"}]},{"tick":183,"events":[{"id":"rocket_boost","instanceId":"evt-d541811d"}]},{"tick":216,"events":[{"id":"earthquake","instanceId":"evt-83c14981"}]},{"tick":228,"events":[{"id":"meteor_strike","instanceId":"evt-2b14bb69"}]},{"tick":234,"events":[{"id":"summon_lightning_strike","instanceId":"evt-85560bfa"}]},{"tick":247,"events":[{"id":"luck_charm","instanceId":"evt-0d08a4d8"}]},{"tick":252,"events":[{"id":"temporary_shield","instanceId":"evt-3fe5de9c"}]},{"tick":265,"events":[{"id":"bomb_throw","instanceId":"evt-4a7a61a1"},{"id":"summon_lightning_strike","instanceId":"evt-dd7fe0c4"}]},{"tick":275,"events":[{"id":"hook_shot","instanceId":"evt-7b648332"},{"id":"chain_reaction","instanceId":"evt-5398d380"}]},{"tick":280,"events":[{"id":"ice_patch","instanceId":"evt-3b00ef8e"}]},{"tick":283,"events":[{"id":"aerial_duel","instanceId":"evt-91f18080"}]},{"tick":298,"events":[{"id":"summon_lightning_strike","instanceId":"evt-633926dc"}]},{"tick":303,"events":[{"id":"smg_attack","instanceId":"evt-27c229f6"}]},{"tick":306,"events":[{"id":"aerial_duel","instanceId":"evt-8d3ba0df"}]},{"tick":309,"events":[{"id":"hook_shot","instanceId":"evt-d590af7c"}]},{"tick":326,"events":[{"id":"temporary_shield","instanceId":"evt-e3eb6eee"}]},{"tick":345,"events":[{"id":"smg_attack","instanceId":"evt-9525aee0"}]},{"tick":347,"events":[{"id":"temporary_shield","instanceId":"evt-43e4ad9f"}]},{"tick":359,"events":[{"id":"samurai_duel","instanceId":"evt-80216c6a"},{"id":"tornado","instanceId":"evt-f666039d"}]},{"tick":367,"events":[{"id":"lightning_strike","instanceId":"evt-5ad32db9"},{"id":"rocket_boost","instanceId":"evt-3c4d7918"}]},{"tick":378,"events":[{"id":"chain_reaction","instanceId":"evt-618e353e"}]},{"tick":395,"events":[{"id":"ice_patch","instanceId":"evt-9ecad5da"}]}]