[{"tick":15,"events":[{"id":"earthquake","instanceId":"evt-599eeede"}]},{"tick":19,"events":[{"id":"lightning_strike","instanceId":"evt-fb99d5ec"}]},{"tick":25,"events":[{"id":"tornado","instanceId":"evt-dee7cfd2"}]},{"tick":37,"events":[{"id":"temporary_shield","instanceId":"evt-ca24516b"}]},{"tick":53,"events":[{"id":"tidal_wave","instanceId":"evt-1d87c9c4"}]},{"tick":58,"events":[{"id":"smg_attack","instanceId":"evt-18827128"}]},{"tick":62,"events":[{"id":"position_swap","instanceId":"evt-823e6c81"},{"id":"summon_lightning_strike","instanceId":"evt-b067f8e5"}]},{"tick":80,"events":[{"id":"magnet_pull","instanceId":"evt-2261bbc3"}]},{"tick":82,"events":[{"id":"hook_shot","instanceId":"evt-6651b114"}]},{"tick":89,"events":[{"id":"tornado","instanceId":"evt-753d1090"}]},{"tick":108,"events":[{"id":"aerial_duel","instanceId":"evt-130ccb2c"}]},{"tick":132,"events":[{"id":"meteor_strike","instanceId":"evt-c27c90bc"}]},{"tick":136,"events":[{"id":"ice_patch","instanceId":"evt-ce9c2bcf"}]},{"tick":137,"events":[{"id":"ufo_abduction","instanceId":"evt-fab35fb0"}]},{"tick":146,"events":[{"id":"chain_reaction","instanceId":"evt-3e4ae118"}]},{"tick":151,"events":[{"id":"summon_lightning_strike","instanceId":"evt-b92f5eca"}]},{"tick":154,"events":[{"id":"samurai_duel","instanceId":"evt-a179a736"}]},{"tick":164,"events":[{"id":"temporary_shield","instanceId":"evt-57772578"}]},{"tick":165,"events":[{"id":"hook_shot","instanceId":"evt-b3d7917e"}]},{"tick":188,"events":[{"id":"bomb_throw","instanceId":"evt-2af29f41"}]},{"tick":189,"events":[{"id":"smg_attack","instanceId":"evt-ae68c002"}]},{"tick":209,"events":[{"id":"temporary_shield","instanceId":"evt-fb940393"}]},{"tick":221,"events":[{"id":"rocket_boost","instanceId":"evt-ea3eab62"},{"id":"lightning_strike","instanceId":"evt-4a2eb5da"}]},{"tick":234,"events":[{"id":"tidal_wave","instanceId":"evt-42c04843"}]},{"tick":237,"events":[{"id":"ice_patch","instanceId":"evt-af7ebfd3"}]},{"tick":250,"events":[{"id":"temporary_shield","instanceId":"evt-a315f56c"}]},{"tick":263,"events":[{"id":"samurai_duel","instanceId":"evt-cfc172e1"}]},{"tick":276,"events":[{"id":"bomb_throw","instanceId":"evt-3893f81e"}]},{"tick":282,"events":[{"id":"position_swap","instanceId":"evt-3ac7b099"}]},{"tick":286,"events":[{"id":"ice_patch","instanceId":"evt-f7aada81"}]},{"tick":288,"events":[{"id":"meteor_strike","instanceId":"evt-6ce8c333"}]},{"tick":298,"events":[{"id":"rocket_boost","instanceId":"evt-2493ba22"}]},{"tick":301,"events":[{"id":"temporary_shield","instanceId":"evt-a86924ab"}]},{"tick":304,"events":[{"id":"bomb_throw","instanceId":"evt-e4c439e1"}]},{"tick":305,"events":[{"id":"hook_shot","instanceId":"evt-be589a22"}]},{"tick":311,"events":[{"id":"luck_charm","instanceId":"evt-924ae815"}]},{"tick":324,"events":[{"id":"earthquake","instanceId":"evt-2a498bad"}]},{"tick":327,"events":[{"id":"magnet_pull","instanceId":"evt-b2814a8f"}]},{"tick":332,"events":[{"id":"smg_attack","instanceId":"evt-4c43214e"}]},{"tick":335,"events":[{"id":"aerial_duel","instanceId":"evt-a5927f59"}]},{"tick":336,"events":[{"id":"hook_shot","instanceId":"evt-e33f5f8b"}]},{"tick":361,"events":[{"id":"chain_reaction","instanceId":"evt-bfdee3f5"}]},{"tick":366,"events":[{"id":"magnet_pull","instanceId":"evt-108a9a10"}]},{"tick":370,"events":[{"id":"hook_shot","instanceId":"evt-af7878e7"}]},{"tick":382,"events":[{"id":"lightning_strike","instanceId":"evt-e934370d"}]}]